InsCode/__init__.py
InsCode/_client.py
InsCode/ai/__init__.py
InsCode/ai/ocr/__init__.py
InsCode/common/__init__.py
InsCode/core/__init__.py
InsCode/core/base.py
InsCode/core/config.py
InsCode/core/exceptions.py
InsCode/core/request_util.py
InsCode/types/__init__.py
InsCode/types/schema.py
InsCode/types/streaming.py
InsCode/util/__init__.py
InsCode/util/typing.py
InsCode-0.2.3.dist-info/LICENSE
InsCode-0.2.3.dist-info/METADATA
InsCode-0.2.3.dist-info/WHEEL
InsCode-0.2.3.dist-info/top_level.txt
InsCode-0.2.3.dist-info/RECORD
