Metadata-Version: 2.1
Name: InsCode
Version: 0.2.3
Summary: InsCode SDK
Author-email: inscode <wanghan@csdn.net>
Classifier: Programming Language :: Python :: 3
Classifier: License :: OSI Approved :: MIT License
Classifier: Operating System :: OS Independent
Requires-Python: >=3
License-File: LICENSE
